OAuthBrowser/__init__.py
OAuthBrowser/__main__.py
OAuthBrowser/browser.py
OAuthBrowser/util.py
OAuthBrowser/wait.py
OAuthBrowser-0.0.1.dist-info/LICENSE.txt
OAuthBrowser-0.0.1.dist-info/METADATA
OAuthBrowser-0.0.1.dist-info/WHEEL
OAuthBrowser-0.0.1.dist-info/top_level.txt
OAuthBrowser-0.0.1.dist-info/RECORD
